cli.py
Package_Version_Manager-1.0.0.data/data/config.yml
Package_Version_Manager-1.0.0.data/data/logging_config.ini
package_version_manager/__init__.py
package_version_manager/constants.py
package_version_manager/directory_crawler.py
package_version_manager/project_repository.py
Package_Version_Manager-1.0.0.dist-info/LICENSE
Package_Version_Manager-1.0.0.dist-info/METADATA
Package_Version_Manager-1.0.0.dist-info/WHEEL
Package_Version_Manager-1.0.0.dist-info/entry_points.txt
Package_Version_Manager-1.0.0.dist-info/top_level.txt
Package_Version_Manager-1.0.0.dist-info/RECORD
