Metadata-Version: 2.1
Name: Package-Version-Manager
Version: 1.0.0
Summary: Package release tool
Home-page: https://github.com/Drakkar-Software/OctoBot
Author: Drakkar-Software
Author-email: drakkar-software@protonmail.com
License: LGPL-3.0
Platform: UNKNOWN
Classifier: Development Status :: 4 - Beta
Classifier: Operating System :: OS Independent
Classifier: Operating System :: MacOS :: MacOS X
Classifier: Operating System :: Microsoft :: Windows
Classifier: Operating System :: POSIX
Classifier: Programming Language :: Python :: 3.7
Requires-Python: >=3.7
Requires-Dist: colorlog
Requires-Dist: PyYAML
Requires-Dist: GitPython
